syslogx/__init__.py
syslogx/__main__.py
syslogx/__meta__.py
syslogx/__version__.py
syslogx/syslogx.py
syslogx-0.12.dist-info/METADATA
syslogx-0.12.dist-info/WHEEL
syslogx-0.12.dist-info/entry_points.txt
syslogx-0.12.dist-info/top_level.txt
syslogx-0.12.dist-info/RECORD
